{
  "id": 112721,
  "url": "https://en.numista.com/112721",
  "title": "2 \"Dicke\" Krone - Christian V",
  "object_type": {
    "id": 1,
    "name": "Standard circulation coins"
  },
  "issuer": {
    "code": "danemark",
    "name": "Denmark"
  },
  "min_year": 1693,
  "max_year": 1696,
  "ruler": [
    {
      "id": 2392,
      "name": "Christian V",
      "wikidata_id": "Q157793",
      "group": {
        "id": 103,
        "name": "House of Oldenburg"
      }
    }
  ],
  "value": {
    "text": "2 Krone",
    "numeric_value": 1.3333333333333333,
    "numerator": 4,
    "denominator": 3,
    "currency": {
      "id": 3466,
      "name": "Rigsdaler specie",
      "full_name": "Rigsdaler specie (1625-1813)"
    }
  },
  "demonetization": {
    "is_demonetized": true
  },
  "size": 25,
  "thickness": 7.8,
  "shape": "Round",
  "composition": {
    "text": "Silver (.833)"
  },
  "obverse": {
    "engravers": [
      "Anton Meybusch"
    ],
    "description": "Bust of King Christian V with curl hairs facing right. Legend divided at sides",
    "lettering": "· CHRIST · V · |  DEI GRATIA ·",
    "lettering_scripts": [
      {
        "name": "Latin"
      }
    ],
    "lettering_translation": "Christian V by the Grace of God",
    "picture": "https://en.numista.com/catalogue/photos/danemark/61c07746425dc5.20115862-original.jpg",
    "thumbnail": "https://en.numista.com/catalogue/photos/danemark/61c07746425dc5.20115862-180.jpg",
    "picture_copyright": "Stack's Bowers"
  },
  "reverse": {
    "engravers": [
      "Anton Meybusch"
    ],
    "description": "Royal crown above King's motto initials. Below the date is divided by a small heart.",
    "lettering": "* DAN · NOR · VAN · GOT · REX \r\n· P · & · I ·\r\n· 16 ♥ 96 ·",
    "lettering_scripts": [
      {
        "name": "Latin"
      }
    ],
    "unabridged_legend": "Daniae Norvegiae Vandalorum Gothorum Rex\r\nPietate et Iustitia",
    "lettering_translation": "King of Denmark (DAN), Norway (NOR), the Wends (VAN) and the Goths (GOT)\r\nWith Piety and Justice",
    "picture": "https://en.numista.com/catalogue/photos/danemark/61c0774680c343.87076619-original.jpg",
    "thumbnail": "https://en.numista.com/catalogue/photos/danemark/61c0774680c343.87076619-180.jpg",
    "picture_copyright": "Stack's Bowers"
  },
  "comments": "Struck as 1 Mark km# 424 but eight times in thickness<br />\r\nThis coin type is often double struck, as seen in pictures",
  "tags": [
    "Crown"
  ],
  "references": [
    {
      "catalogue": {
        "id": 3,
        "code": "KM"
      },
      "number": "A430"
    }
  ],
  "weight": 35.977,
  "edge": {
    "description": "Plain",
    "picture": "https://en.numista.com/catalogue/photos/danemark/3122-original.jpg",
    "thumbnail": "https://en.numista.com/catalogue/photos/danemark/3122-180.jpg",
    "picture_copyright": "Stacks Bowers",
    "picture_copyright_url": "http://www.stacksbowers.com/"
  },
  "mints": [
    {
      "id": 260,
      "name": "Royal Danish Mint"
    }
  ],
  "category": "coin",
  "type": "Standard circulation coins"
}