{
  "id": 24533,
  "url": "https://en.numista.com/24533",
  "title": "2 Rigsbankskilling - Christian VIII",
  "object_type": {
    "id": 1,
    "name": "Standard circulation coins"
  },
  "issuer": {
    "code": "danemark",
    "name": "Denmark"
  },
  "min_year": 1842,
  "max_year": 1842,
  "ruler": [
    {
      "id": 2398,
      "name": "Christian VIII",
      "wikidata_id": "Q157781",
      "group": {
        "id": 103,
        "name": "House of Oldenburg"
      }
    }
  ],
  "value": {
    "text": "2 Rigsbankskilling",
    "numeric_value": 0.020833333333333332,
    "numerator": 1,
    "denominator": 48,
    "currency": {
      "id": 3467,
      "name": "Rigsbankdaler",
      "full_name": "Rigsbankdaler (1813-1854)"
    }
  },
  "demonetization": {
    "is_demonetized": true
  },
  "size": 28.6,
  "shape": "Round",
  "composition": {
    "text": "Copper"
  },
  "technique": {
    "text": "Milled"
  },
  "obverse": {
    "engravers": [
      "Frederik Christopher Krohn"
    ],
    "description": "Portrait of King Christian VIII facing right",
    "lettering": "CHRISTIANVS VIII D:G:DANIÆ V:G:REX\r\nF.K.",
    "lettering_scripts": [
      {
        "name": "Latin"
      }
    ],
    "lettering_translation": "Christian VIII by the Grace of God, King of Denmark, of the Goths and the Wends",
    "picture": "https://en.numista.com/catalogue/photos/danemark/3382-original.jpg",
    "thumbnail": "https://en.numista.com/catalogue/photos/danemark/3382-180.jpg",
    "picture_copyright": "Heritage Auctions",
    "picture_copyright_url": "http://www.ha.com"
  },
  "reverse": {
    "description": "Crossed sword and scepter with Crown of Denmark above; below the value with date at left and mintmarks at right.",
    "lettering": "2\r\n1842   R:B:S  ♔ V.S.",
    "lettering_scripts": [
      {
        "name": "Latin"
      }
    ],
    "picture": "https://en.numista.com/catalogue/photos/danemark/3383-original.jpg",
    "thumbnail": "https://en.numista.com/catalogue/photos/danemark/3383-180.jpg",
    "picture_copyright": "Heritage Auctions",
    "picture_copyright_url": "http://www.ha.com"
  },
  "tags": [
    "Monarch",
    "Crown",
    "Cold weapons"
  ],
  "references": [
    {
      "catalogue": {
        "id": 3,
        "code": "KM"
      },
      "number": "728"
    }
  ],
  "weight": 14.616,
  "orientation": "medal",
  "mints": [
    {
      "id": 260,
      "name": "Royal Danish Mint"
    }
  ],
  "category": "coin",
  "type": "Standard circulation coins"
}