{
  "id": 76689,
  "url": "https://en.numista.com/76689",
  "title": "24 Skilling Dansk - Christian VI (Bust type)",
  "object_type": {
    "id": 1,
    "name": "Standard circulation coins"
  },
  "issuer": {
    "code": "danemark",
    "name": "Denmark"
  },
  "min_year": 1731,
  "max_year": 1732,
  "ruler": [
    {
      "id": 2394,
      "name": "Christian VI",
      "wikidata_id": "Q154993",
      "group": {
        "id": 103,
        "name": "House of Oldenburg"
      }
    }
  ],
  "value": {
    "text": "24 Skilling",
    "numeric_value": 0.25,
    "numerator": 1,
    "denominator": 4,
    "currency": {
      "id": 3466,
      "name": "Rigsdaler specie",
      "full_name": "Rigsdaler specie (1625-1813)"
    }
  },
  "demonetization": {
    "is_demonetized": true,
    "demonetization_date": "1873-05-27"
  },
  "size": 29.6,
  "shape": "Round",
  "composition": {
    "text": "Silver (.562)"
  },
  "obverse": {
    "description": "Armored bust of King facing right. King has a full peruke and wears a necklace with pendant of the Order of the Elephant.",
    "lettering": "CHRIST • VI • D • G •      REX •   DAN • NORV  • V • G •",
    "lettering_scripts": [
      {
        "name": "Latin"
      }
    ],
    "unabridged_legend": "Christian VI Dei Gratia Rex Daniae Norvegiae Vandalorum Gothorum",
    "lettering_translation": "Christian VI, By the Grace of God, King of Denmark, Norway, the Wends and the Goths.",
    "picture": "https://en.numista.com/catalogue/photos/danemark/620e87b6a0aa25.37298597-original.jpg",
    "thumbnail": "https://en.numista.com/catalogue/photos/danemark/620e87b6a0aa25.37298597-180.jpg",
    "picture_copyright": "Heritage Auctions",
    "picture_copyright_url": "http://www.ha.com"
  },
  "reverse": {
    "description": "Crowned three-parted shield with arms of Denmark, Sweden and Norway above big cross divides date and mintmark, value in legend.",
    "lettering": "24 • SKILLING •   DANSKE • COUR: M •\r\n17  32\r\nC  W",
    "lettering_scripts": [
      {
        "name": "Latin"
      }
    ],
    "unabridged_legend": "24 Skilling Danske Courant M 1732 C W",
    "picture": "https://en.numista.com/catalogue/photos/danemark/620e87b6dd6c74.51419430-original.jpg",
    "thumbnail": "https://en.numista.com/catalogue/photos/danemark/620e87b6dd6c74.51419430-180.jpg",
    "picture_copyright": "Heritage Auctions",
    "picture_copyright_url": "http://www.ha.com"
  },
  "comments": "Version with heart on crossbar<br />\r\n<a href=\"https://en.numista.com/catalogue/images/5937c19e1c1eb.jpg\"><img src=\"https://en.numista.com/catalogue/images/miniatures/5937c19e1c1eb.jpg\" alt=\"\" width=\"200\" height=\"200\" /></a>",
  "tags": [
    "Coat of Arms"
  ],
  "references": [
    {
      "catalogue": {
        "id": 3,
        "code": "KM"
      },
      "number": "536"
    }
  ],
  "weight": 9.66,
  "mints": [
    {
      "id": 5316,
      "name": "Copenhagen"
    }
  ],
  "category": "coin",
  "type": "Standard circulation coins"
}