{
  "id": 83077,
  "url": "https://en.numista.com/83077",
  "title": "1 Christian d'Or - Christian IX",
  "object_type": {
    "id": 1,
    "name": "Standard circulation coins"
  },
  "issuer": {
    "code": "danemark",
    "name": "Denmark"
  },
  "min_year": 1869,
  "max_year": 1869,
  "ruler": [
    {
      "id": 2400,
      "name": "Christian IX",
      "wikidata_id": "Q151305",
      "group": {
        "id": 104,
        "name": "House of Schleswig-Holstein-Sonderburg-Glücksburg"
      }
    }
  ],
  "value": {
    "text": "1 Christian d'Or ",
    "numeric_value": 5,
    "currency": {
      "id": 3364,
      "name": "Rigsdaler rigsmont",
      "full_name": "Rigsdaler rigsmont (1854-1873)"
    }
  },
  "demonetization": {
    "is_demonetized": true
  },
  "size": 22.5,
  "shape": "Round",
  "composition": {
    "text": "Gold (.896)"
  },
  "technique": {
    "text": "Milled"
  },
  "obverse": {
    "engravers": [
      "Harald Conradsen"
    ],
    "description": "Portrait of Christian IX facing right. Initials of the engraver of neck-cut.",
    "lettering": "CHRISTIANVS IX D : G : DANIÆ V : G : REX",
    "lettering_scripts": [
      {
        "name": "Latin"
      }
    ],
    "lettering_translation": "Christian IX, by the Grace of God, King of Denmark, of the Wends and the Goths",
    "picture": "https://en.numista.com/catalogue/photos/danemark/62be94ee7ebbb9.77141452-original.jpg",
    "thumbnail": "https://en.numista.com/catalogue/photos/danemark/62be94ee7ebbb9.77141452-180.jpg",
    "picture_copyright": "Heritage Auctions",
    "picture_copyright_url": "http://www.ha.com"
  },
  "reverse": {
    "description": "Crowned grater shield with Arms of Denmark and its territories (adorned with the collar of the Order of the Elephant only below shield) held by wildmen armed with clubs at sides. A wide crowned mantle is behind shield and supporters. Value above while date is below shield with mintmark at sides.",
    "lettering": "1 CHR: D'OR\r\n♔18  |  69. CS",
    "lettering_scripts": [
      {
        "name": "Latin"
      }
    ],
    "picture": "https://en.numista.com/catalogue/photos/danemark/62be94eed320f9.91835973-original.jpg",
    "thumbnail": "https://en.numista.com/catalogue/photos/danemark/62be94eed320f9.91835973-180.jpg",
    "picture_copyright": "Heritage Auctions",
    "picture_copyright_url": "http://www.ha.com"
  },
  "tags": [
    "Monarch",
    "Crown",
    "Coat of Arms"
  ],
  "references": [
    {
      "catalogue": {
        "id": 3,
        "code": "KM"
      },
      "number": "778"
    },
    {
      "catalogue": {
        "id": 11,
        "code": "Fr"
      },
      "number": "294"
    }
  ],
  "weight": 6.642,
  "mints": [
    {
      "id": 260,
      "name": "Royal Danish Mint"
    }
  ],
  "category": "coin",
  "type": "Standard circulation coins"
}