{
  "id": "c4h56",
  "ruler_volume": "c4h",
  "ruler_inferred": "Christian 4.",
  "page_title": "Christian 4., Hede 56",
  "ruler": "Christian 4.",
  "mint": "København",
  "nominal": "2 speciedaler",
  "specs": {
    "default": {
      "bruttovægt_g": 58.464,
      "finhed": 0.881,
      "finvægt_g": 51.562,
      "marken_fin_udbragt_til": {
        "value": 9.071,
        "unit": "speciedalere"
      }
    }
  },
  "catalog_refs": {
    "Hede": [
      "56",
      "56A",
      "56B",
      "56C",
      "56D"
    ],
    "Sieg": [
      "124"
    ],
    "Schou": [
      "8-9",
      "1-2,3-4",
      "6",
      "2",
      "10",
      "11"
    ]
  },
  "eksemplarer": {
    "Zincksamlingen": [
      "1624, Schou 6",
      "1626, Schou 2",
      "1628, Schou 10",
      "1628, Schou 11",
      "§§HR§§"
    ]
  },
  "description": "Forside: brystbillede, bagside: ovale provinsvåben\nA) 1624, 1626 (RR), 1627 (R), 1628 (RR); Møntmærke trekløver: \n, \nNS\n(Hede 56A, Schou hhv. 6-7, 2-3, 5-7 og 10-12, Sieg 124.1)\nB) 1627; Møntmærke trekløver: \n, \nBZ\n(Hede 56B, Schou 8-9, Sieg 124.2)\nC) 1631 (R), 1632 (RR), 1634 (RRR); Møntmærke trekløver: \n, \nPG\n(Hede 56C, Schou 1-2, 3-4 og 2, Sieg 124.3)\nD) 1647 (RRR); Intet møntmærke, \nHK\n(Hede 56D, Schou 8-9, Sieg 124.4)",
  "hede_numbers_filename": [
    "56"
  ],
  "hede_numbers_title": [
    "56"
  ],
  "raw_text": "Christian 4., Hede 56\nChristian 4., 2 speciedaler, København\nForside: brystbillede, bagside: ovale provinsvåben\nA) 1624, 1626 (RR), 1627 (R), 1628 (RR); Møntmærke trekløver: \n, \nNS\n(Hede 56A, Schou hhv. 6-7, 2-3, 5-7 og 10-12, Sieg 124.1)\nB) 1627; Møntmærke trekløver: \n, \nBZ\n(Hede 56B, Schou 8-9, Sieg 124.2)\nC) 1631 (R), 1632 (RR), 1634 (RRR); Møntmærke trekløver: \n, \nPG\n(Hede 56C, Schou 1-2, 3-4 og 2, Sieg 124.3)\nD) 1647 (RRR); Intet møntmærke, \nHK\n(Hede 56D, Schou 8-9, Sieg 124.4)\n\nBruttovægt: 58,464g\nFinhed: 0,881\nFinvægt: 51,562g\nMarken fin udbragt til 9,071 speciedalere\n\nEksemplarer fra Zincksamlingen:\nHede 56A:\n1624, Schou 6\n1626, Schou 2\n1628, Schou 10\n1628, Schou 11\n\nTilbage til Dansk Mønt"
}