{
  "id": "f2h27",
  "ruler_volume": "f2h",
  "ruler_inferred": "Frederik 2.",
  "page_title": "Frederik 2., Hede 27",
  "ruler": "Frederik 2.",
  "nominal": "2 Skilling",
  "mint": "Frederiksborg",
  "years": [
    {
      "year": 1585,
      "rarity": null
    },
    {
      "year": 1582,
      "rarity": null
    }
  ],
  "catalog_refs": {
    "Frederik": [
      "2"
    ],
    "Hede": [
      "27"
    ],
    "Sieg": [
      "8"
    ],
    "Schou": [
      "6",
      "7",
      "2"
    ]
  },
  "litteratur": [
    "Vendeltoft, O. P.: Mange danske mønter er præget i Hillerød. I: Frederiksborg Banks blad Bindestregen 1971; Møntsamlernyt 6,1971",
    "§§HR§§"
  ],
  "eksemplarer": {
    "Zincksamlingen": [
      "1582, Schou 7",
      "1585, Schou 2",
      "§§HR§§"
    ]
  },
  "description": "Forside: Danmarks våben, bagside: værdiangivelse (Hede 27, Schou hhv. 6-15, 12-18 og 2, Sieg 8)\nDer blev under Frederik 2. præget mønter af følgende værdier på Frederiksborg: 1 mark, 8 skilling, 2 skilling,\n1 skilling og i hvid. Lederen af møntværkstedet var møntmester \nPoul Gulden\n,\nder forestod udmøntningen af Frederiksborg mønter indtil 1585, på hvilket\ntidspunkt møntværkstedet blev nedlagt.\n\nVægt: 2,338g\nFinhed: 0,312\nFinvægt: 0,731g\nMarken fin udbragt til 10,000 daler",
  "hede_numbers_filename": [
    "27"
  ],
  "hede_numbers_title": [
    "27"
  ],
  "raw_text": "Frederik 2., Hede 27\nFrederik 2.\n2 Skilling, Frederiksborg\n(15)82, (15)83, (15)85. Forside: Danmarks våben, bagside: værdiangivelse (Hede 27, Schou hhv. 6-15, 12-18 og 2, Sieg 8)\nDer blev under Frederik 2. præget mønter af følgende værdier på Frederiksborg: 1 mark, 8 skilling, 2 skilling,\n1 skilling og i hvid. Lederen af møntværkstedet var møntmester \nPoul Gulden\n,\nder forestod udmøntningen af Frederiksborg mønter indtil 1585, på hvilket\ntidspunkt møntværkstedet blev nedlagt.\n\nVægt: 2,338g\nFinhed: 0,312\nFinvægt: 0,731g\nMarken fin udbragt til 10,000 daler\n\nEksemplar fra Bondes samling:\n1582, Schou 6\n\nEksemplarer fra Zincksamlingen:\n1582, Schou 7\n1585, Schou 2\n\nLitteratur:\nVendeltoft, O. P.: Mange danske mønter er præget i Hillerød. I: Frederiksborg Banks blad Bindestregen 1971; Møntsamlernyt 6,1971\n\nTilbage til Dansk Mønt"
}