{
  "id": "f4h6",
  "ruler_volume": "f4h",
  "ruler_inferred": "Frederik 4.",
  "page_title": "Frederik 4., Hede 6 og 7",
  "ruler": "Frederik 4.",
  "years": [
    {
      "year": 1700,
      "rarity": null
    }
  ],
  "nominal": "1 og 3 Dukat",
  "mint": "København",
  "specs": {
    "by_hede": {
      "6": {
        "bruttovægt_g": 3.49,
        "finhed": 0.979,
        "finvægt_g": 3.418
      },
      "7": {
        "bruttovægt_g": 10.471,
        "finhed": 0.979,
        "finvægt_g": 10.252
      }
    }
  },
  "catalog_refs": {
    "Frederik": [
      "4"
    ],
    "Hede": [
      "6",
      "7"
    ],
    "Schou": [
      "3-4",
      "2",
      "3",
      "4"
    ],
    "Sieg": [
      "39",
      "40"
    ]
  },
  "eksemplarer": {
    "Zincksamlingen": [
      "1700, Schou 3",
      "1700, Schou 4",
      "§§HR§§"
    ]
  },
  "description": "Forside: portræt, bagside: monogram\n1 Dukat\nHede 6, Schou 3-4, sølvafslag 3a, Sieg 39",
  "hede_numbers_filename": [
    "6"
  ],
  "hede_numbers_title": [
    "6"
  ],
  "raw_text": "Frederik 4., Hede 6 og 7\nFrederik 4.\n1 og 3 Dukat 1700, København\nForside: portræt, bagside: monogram\n1 Dukat\nHede 6, Schou 3-4, sølvafslag 3a, Sieg 39\nBruttovægt: 3,490g\nFinhed: 0,979\nFinvægt: 3,418g\n3 Dukat (unik)\nHede 7, Schou 2, Sieg 40\nBruttovægt: 10,471g\nFinhed: 0,979\nFinvægt: 10,252g\n\nEksemplarer fra Zincksamlingen:\nHede 6:\n1700, Schou 3\n1700, Schou 4\n\nTilbage til Dansk Mønt"
}