{
  "id": "f9h15",
  "ruler_volume": "f9h",
  "ruler_inferred": "Frederik 9.",
  "page_title": "f9h14b",
  "ruler": "Frederik 9.",
  "years": [
    {
      "year": 1960,
      "rarity": null
    },
    {
      "year": 1961,
      "rarity": null
    },
    {
      "year": 1962,
      "rarity": null
    },
    {
      "year": 1963,
      "rarity": null
    },
    {
      "year": 1964,
      "rarity": null
    },
    {
      "year": 1965,
      "rarity": null
    },
    {
      "year": 1966,
      "rarity": null
    },
    {
      "year": 1967,
      "rarity": null
    },
    {
      "year": 1968,
      "rarity": null
    },
    {
      "year": 1969,
      "rarity": null
    },
    {
      "year": 1970,
      "rarity": null
    },
    {
      "year": 1971,
      "rarity": null
    },
    {
      "year": 1972,
      "rarity": null
    }
  ],
  "nominal": "5 øre",
  "mint": "København",
  "catalog_refs": {
    "Frederik": [
      "9"
    ],
    "Hede": [
      "15"
    ],
    "Sieg": [
      "6.1",
      "6.2"
    ]
  },
  "hede_numbers_filename": [
    "15"
  ],
  "raw_text": "f9h14b\nFrederik 9.\n5 øre 1960-72, København\nForside monogram, bagside værdiangivelse, kornaks. Bronze\nA) 1960, 1962-71; Møntmestermærke: \nC\n(Hede 15, Sieg 6.1)\nB) 1972; Møntmestermærke: \nS\n(Hede 15, Sieg 6.2)\nVægt: 6,0g\n\nTilbage til Dansk Mønt"
}