{"ikmk_mds_id":"18247265","ikmk_id":"48785","eLearning_completed":"0","primary_source_id":"0","title":"Trier: Bruno von Bretten und Laufen","inventory_number":"","activated":"yes","item":{"ikmk_item_id":"1","ndp_uri":"https:\/\/ikmk.smb.museum\/ndp\/item\/1","item_de":"M\u00fcnze","item_en":"Coin","item_nomisma":"http:\/\/nomisma.org\/id\/coin"},"permalink":"https:\/\/ikmk.smb.museum\/object?id=18247265","permalink_source":null,"publisher":{"ikmk_publisher_id":13,"ndp_uri":"https:\/\/ikmk.smb.museum\/ndp\/owner\/13","publisher_name":"M\u00fcnzkabinett, Staatliche Museen zu Berlin - Stiftung Preu\u00dfischer Kulturbesitz","publisher_isil":"http:\/\/ld.zdb-services.de\/resource\/organisations\/DE-MUS-814819","publisher_isil_short":"DE-MUS-814819","UID":"http:\/\/ld.zdb-services.de\/resource\/organisations\/DE-MUS-814819\/18247265","legalBodyWeblink":"https:\/\/www.smb.museum\/museen-und-einrichtungen\/muenzkabinett\/home.html","nomisma_address":"http:\/\/nomisma.org\/id\/mk_berlin","author":"Kluge, Bernd; Schauer, Burkhard"},"owner":{"ikmk_owner_id":"13","owner_name":"Berlin, M\u00fcnzkabinett der Staatlichen Museen","owner_isil":"http:\/\/ld.zdb-services.de\/resource\/organisations\/DE-MUS-814819","owner_isil_short":"DE-MUS-814819","owner_www_address":"https:\/\/ikmk.smb.museum\/","nomisma_address":"http:\/\/nomisma.org\/id\/mk_berlin","ndp_uri":"https:\/\/ikmk.smb.museum\/ndp\/owner\/13","owner_type":{"de":"Eigentum","en":"Property","ikmk_type_id":"2","ndp_uri":"https:\/\/ikmk.smb.museum\/ndp\/status_of_property\/2"}},"ikmk_status_id":"7","status":{"de":"vorhanden","en":"present","ikmk_status_id":"7","ndp_uri":"https:\/\/ikmk.smb.museum\/ndp\/object_status\/7"},"nominal":{"ikmk_nominal_id":"1304","nominal_de":"Denar (MA)","nominal_en":"Denarius (MA)","nominal_nomisma_id":"http:\/\/nomisma.org\/id\/medieval_denarius","nominal_gnd_id":"http:\/\/d-nb.info\/gnd\/4174023-3","info_de":"","info_en":"","ndp_uri":"https:\/\/ikmk.smb.museum\/ndp\/denomination\/1304"},"patronage":"Christian Stoess","date_last":"2023-03-14 01:49:51","coin_status":[{"ikmk_coin_status_id":"16","coin_status_name_de":"Erzbistum","coin_status_name_en":"Archbishopric","coin_status_nomisma_id":"http:\/\/nomisma.org\/id\/archbishop","ndp_uri":"https:\/\/ikmk.smb.museum\/ndp\/class_status\/16"}],"mint":[{"ikmk_country_id":"19","country_ndp_url":"https:\/\/ikmk.smb.museum\/ndp\/country\/19","country_name_de":"Deutschland","country_name_en":"Germany","country_nomisma_id":"http:\/\/nomisma.org\/id\/bundesrepublik_deutschland","country_geoname_id":"http:\/\/www.geonames.org\/2921044","ikmk_region_id":"496","region_ndp_uri":"https:\/\/ikmk.smb.museum\/ndp\/region\/496","region_name":"Oberlothringen","region_nomisma_id":"","region_geoname_id":"","ikmk_mint_id":"270","mint_ndp_uri":"https:\/\/ikmk.smb.museum\/ndp\/location\/270","mint_name":"Trier","mint_name_de":"Trier","mint_name_en":null,"mint_nomisma_id":"http:\/\/nomisma.org\/id\/treveri","mint_geoname_id":"http:\/\/www.geonames.org\/3247911"}],"material":{"ikmk_material_id":"1","material_name_de":"Silber","material_name_en":"Silver","material_nomisma_id":"http:\/\/nomisma.org\/id\/ar","ndp_uri":"https:\/\/ikmk.smb.museum\/ndp\/material\/1"},"diameter":"19 mm","die_axis":"12 h","weight":"0.75 g","accession":"2014\/254","access_year":"2014","access_type":{"ikmk_access_type_id":"3","access_type_name":"Schenkung","access_type_nomisma_id":"","access_type_concept_id":"http:\/\/d-nb.info\/gnd\/4052258-1","ndp_uir":"https:\/\/ikmk.smb.museum\/ndp\/accession\/3"},"findspot":{"ikmk_country_id":"10","country_ndp_id":"https:\/\/ikmk.smb.museum\/ndp\/country\/10","country_name_de":"Belgien","country_name_en":"Belgium","country_nomisma_id":"","country_geoname_id":"http:\/\/www.geonames.org\/2802361","ikmk_findspot_id":"1300","findspot_ndp_uri":"https:\/\/ikmk.smb.museum\/ndp\/location\/1300","findspot_name":"B\u00e9bange","findspot_nomisma_id":"","findspot_geonames_id":"http:\/\/www.geonames.org\/2802478"},"provenienz_extern":"","acquisition_date":"30.09.2014","avers":{"leg_trans":"S retrograd","leg_text":"+ RV[NIO ARCHIE]PISCOBV","image_description":"Barh\u00e4uptiges Brustbild Erzbischof Brunos nach links, davor Kreuzstab.","foto_date":"2015-02-03","photographer":{"ikmk_photographer_id":"5","photographer_name":"Reinhard Saczewski","photographer_gnd":"","photographer_viaf":""},"path_thumbnail":"https:\/\/ikmk.smb.museum\/image\/18247265\/vs_opt.jpg","path_opt":"https:\/\/ikmk.smb.museum\/image\/18247265\/vs_opt.jpg","path_opt_rel":"\/data\/www\/001-ikmk\/mk-edit\/images\/n48\/48785\/vs_opt.jpg","path":"https:\/\/ikmk.smb.museum\/image\/18247265\/vs_org.jpg","path_org":"https:\/\/ikmk.smb.museum\/image\/18247265\/vs_org.jpg","image_timestamp":1643739835,"copyright":{"short":"PDM 1.0","url":"https:\/\/creativecommons.org\/publicdomain\/mark\/1.0\/","de":"Bilddateien sind lizenziert als&nbsp;<a href=\"https:\/\/creativecommons.org\/publicdomain\/mark\/1.0\/deed.de\" target=\"_blank\">Public Domain Mark 1.0<\/a>. Berlin, M\u00fcnzkabinett der Staatlichen Museen, 18247265. Aufnahme durch Reinhard Saczewski.","en":"Image files are licensed&nbsp;<a href=\"https:\/\/creativecommons.org\/publicdomain\/mark\/1.0\/deed.en\" target=\"_blank\">Public Domain Mark 1.0<\/a>. Berlin, M\u00fcnzkabinett der Staatlichen Museen, 18247265. Photographs by Reinhard Saczewski."}},"revers":{"leg_trans":"","leg_text":"TR[EVERIS]","image_description":"Brustbild eines Engels von vorn. \u00dcber dem Kopf zwei Sterne, unten Stadtname.","foto_date":"2015-02-03","photographer":{"ikmk_photographer_id":"5","photographer_name":"Reinhard Saczewski","photographer_gnd":"","photographer_viaf":""},"path_thumbnail":"https:\/\/ikmk.smb.museum\/image\/18247265\/rs_opt.jpg","path_opt":"https:\/\/ikmk.smb.museum\/image\/18247265\/rs_opt.jpg","path_opt_rel":"\/data\/www\/001-ikmk\/mk-edit\/images\/n48\/48785\/rs_opt.jpg","path":"https:\/\/ikmk.smb.museum\/image\/18247265\/rs_org.jpg","path_org":"https:\/\/ikmk.smb.museum\/image\/18247265\/rs_org.jpg","image_timestamp":1643739835,"copyright":{"short":"PDM 1.0","url":"https:\/\/creativecommons.org\/publicdomain\/mark\/1.0\/","de":"Bilddateien sind lizenziert als&nbsp;<a href=\"https:\/\/creativecommons.org\/publicdomain\/mark\/1.0\/deed.de\" target=\"_blank\">Public Domain Mark 1.0<\/a>. Berlin, M\u00fcnzkabinett der Staatlichen Museen, 18247265. Aufnahme durch Reinhard Saczewski.","en":"Image files are licensed&nbsp;<a href=\"https:\/\/creativecommons.org\/publicdomain\/mark\/1.0\/deed.en\" target=\"_blank\">Public Domain Mark 1.0<\/a>. Berlin, M\u00fcnzkabinett der Staatlichen Museen, 18247265. Photographs by Reinhard Saczewski."}},"division":{"ikmk_division_id":"2","division_name_de":"Mittelalter","division_name_en":"Medieval Period"},"sub_division":{"ikmk_subdivision_id":"19","subdivision_name_de":"Hochmittelalter","subdivision_name_en":"High Middle Ages"},"literatur":"H. Dannenberg, Die deutschen M\u00fcnzen der s\u00e4chsischen und fr\u00e4nkischen Kaiserzeit (1876-1905) Nr. 484; R. Weiller, Die M\u00fcnzen von Trier I (1988) Nr. 104 Phase 2; B. Kluge, CNG (198\/2000) Nr. 17.32.2; B. Kluge, Ein Nachtrag zum Fund von B\u00e9bange, Geldgeschichtliche Nachrichten 50, 2015, 215-226 Nr. 35 (dieses St\u00fcck).","comment":"","period":{"ikmk_period_id":"14","name_de":"Hochmittelalter","name_en":"High Middle Ages","description_de":"Bezeichnung der Epoche zwischen 900 (teilweise auch 1000) und der Mitte des 13. Jahrhunderts.","description_en":"Term to describe the period between 900 (in some cases 1000) and the middle of the 13th century.","concept_id":"http:\/\/d-nb.info\/gnd\/7503822-5","ndp_uri":"https:\/\/ikmk.smb.museum\/ndp\/period\/14"},"year_start":"1110","year_end":"1120","date_verbal":"ca. 1110-1120","year_islam":"0","references":[{"ikmk_referenz_id":201,"souce":"Dannenberg","number":"0484","similar":"0"}],"manufacturing":[{"ikmk_manufacturing_id":"21","manufacturing_name_de":"gepr\u00e4gt","manufacturing_name_en":"struck","nomisma_id":"http:\/\/nomisma.org\/id\/struck","ndp_uri":"https:\/\/ikmk.smb.museum\/ndp\/manufacture\/21"}],"linked_persons_corporations":{"54":{"ikmk_type_id":"54","type_name_de":"Dargestellte\/r","type_name_en":"Sitter","type_nomisma_id":"http:\/\/nomisma.org\/id\/portrait","type_concept_id":"http:\/\/vocab.getty.edu\/aat\/300189844","ndp_id":"https:\/\/ikmk.smb.museum\/ndp\/type_for_person_and_corporation\/54","items":{"406":{"ikmk_person_id":"406","title_de":null,"first_name_de":null,"last_name_de":"Bruno von Bretten und Laufen (1102-1124), Erzbischof von Trier","vitalDates":"-25.04.1124","title_en":null,"first_name_en":null,"last_name_en":"Bruno of Bretten and Laufen (1102-1124), archbishop of Trier","corporation":"0","lod":{"https:\/\/d-nb.info\/gnd\/102425817":"https:\/\/d-nb.info\/gnd\/102425817","https:\/\/de.wikipedia.org\/wiki\/Bruno_von_Bretten":"https:\/\/de.wikipedia.org\/wiki\/Bruno_von_Bretten","https:\/\/en.wikipedia.org\/wiki\/Bruno_(archbishop_of_Trier)":"https:\/\/en.wikipedia.org\/wiki\/Bruno_(archbishop_of_Trier)","https:\/\/viaf.org\/viaf\/27456296":"https:\/\/viaf.org\/viaf\/27456296","https:\/\/www.wikidata.org\/wiki\/Q993987":"https:\/\/www.wikidata.org\/wiki\/Q993987","https:\/\/ikmk.smb.museum\/ndp\/person\/406":"https:\/\/ikmk.smb.museum\/ndp\/person\/406"}}}},"57":{"ikmk_type_id":"57","type_name_de":"Autorit\u00e4t","type_name_en":"Authority","type_nomisma_id":"http:\/\/nomisma.org\/id\/authority","type_concept_id":"http:\/\/d-nb.info\/gnd\/1051614252","ndp_id":"https:\/\/ikmk.smb.museum\/ndp\/type_for_person_and_corporation\/57","items":{"406":{"ikmk_person_id":"406","title_de":null,"first_name_de":null,"last_name_de":"Bruno von Bretten und Laufen (1102-1124), Erzbischof von Trier","vitalDates":"-25.04.1124","title_en":null,"first_name_en":null,"last_name_en":"Bruno of Bretten and Laufen (1102-1124), archbishop of Trier","corporation":"0","lod":{"https:\/\/d-nb.info\/gnd\/102425817":"https:\/\/d-nb.info\/gnd\/102425817","https:\/\/de.wikipedia.org\/wiki\/Bruno_von_Bretten":"https:\/\/de.wikipedia.org\/wiki\/Bruno_von_Bretten","https:\/\/en.wikipedia.org\/wiki\/Bruno_(archbishop_of_Trier)":"https:\/\/en.wikipedia.org\/wiki\/Bruno_(archbishop_of_Trier)","https:\/\/viaf.org\/viaf\/27456296":"https:\/\/viaf.org\/viaf\/27456296","https:\/\/www.wikidata.org\/wiki\/Q993987":"https:\/\/www.wikidata.org\/wiki\/Q993987","https:\/\/ikmk.smb.museum\/ndp\/person\/406":"https:\/\/ikmk.smb.museum\/ndp\/person\/406"}}}},"125":{"ikmk_type_id":"125","type_name_de":"Ver\u00e4u\u00dferer (an Museum)","type_name_en":"Vendor (to Museum)","type_nomisma_id":"","type_concept_id":"http:\/\/d-nb.info\/gnd\/4126928-7","ndp_id":"https:\/\/ikmk.smb.museum\/ndp\/type_for_person_and_corporation\/125","items":{"5545":{"ikmk_person_id":"5545","title_de":null,"first_name_de":null,"last_name_de":"Dr. Busso Peus Nachfolger (Frankfurt am Main)","vitalDates":null,"title_en":null,"first_name_en":null,"last_name_en":"Dr. Busso Peus Nachfolger (Frankfurt am Main)","corporation":"1","lod":{"https:\/\/d-nb.info\/gnd\/2040972-2":"https:\/\/d-nb.info\/gnd\/2040972-2","https:\/\/viaf.org\/viaf\/144898260":"https:\/\/viaf.org\/viaf\/144898260","https:\/\/ikmk.smb.museum\/ndp\/corporation\/5545":"https:\/\/ikmk.smb.museum\/ndp\/corporation\/5545"}}}}},"keywords":[{"ikmk_keyword_id":"50","keyword_de":"Christliche Ikonographie","keyword_gnd_uri":"http:\/\/d-nb.info\/gnd\/7502667-3","keyword_concept_uri":""},{"ikmk_keyword_id":"18","keyword_de":"Deutschland","keyword_gnd_uri":"http:\/\/d-nb.info\/gnd\/4011882-4","keyword_concept_uri":"http:\/\/vocab.getty.edu\/tgn\/7000084"},{"ikmk_keyword_id":"37","keyword_de":"Geistliche F\u00fcrsten","keyword_gnd_uri":"http:\/\/d-nb.info\/gnd\/4156371-2","keyword_concept_uri":"https:\/\/nomisma.org\/id\/clergy"},{"ikmk_keyword_id":"9","keyword_de":"Hochmittelalter, 10.-12. Jh.","keyword_gnd_uri":"http:\/\/d-nb.info\/gnd\/7503822-5","keyword_concept_uri":""},{"ikmk_keyword_id":"2","keyword_de":"Mittelalter","keyword_gnd_uri":"http:\/\/d-nb.info\/gnd\/4129108-6","keyword_concept_uri":"http:\/\/vocab.getty.edu\/aat\/300020756"},{"ikmk_keyword_id":"43","keyword_de":"Portr\u00e4ts","keyword_gnd_uri":"http:\/\/d-nb.info\/gnd\/4006627-7","keyword_concept_uri":"http:\/\/vocab.getty.edu\/aat\/300015637"},{"ikmk_keyword_id":"69","keyword_de":"Silber","keyword_gnd_uri":"http:\/\/d-nb.info\/gnd\/4133759-1","keyword_concept_uri":"http:\/\/www.nomisma.org\/id\/ar"}],"timeline_themes":[{"ikmk_timeline_id":"94","timeline_item":"Deutschland im Hochmittelalter","description":"Das ostfr\u00e4nkisch-deutsche Reich war um 900 rechtsrheinisch eine Region ohne eigene M\u00fcnzpr\u00e4gung. Mit dem politischen Aufschwung unter den Ottonen (919-1024) und Saliern (1024-1125) verschob sich nicht nur die Grenze der M\u00fcnzgeldwirtschaft innerhalb weniger Jahrzehnte vom Rhein an die Elbe, sondern wurde das Reich der Ottonen und Salier zum Hauptm\u00fcnzproduzent in Europa. An der M\u00fcnzpr\u00e4gung wurde vom K\u00f6nigtum durch gezielte Privilegien die Reichskirche beteiligt. Neben den Emissionen, die sich durch Namensnennung K\u00f6nig, Geistlichkeit oder weltlichem Adel zuweisen lassen, spielen anonyme Emissionen eine gro\u00dfe Rolle, vor allem im Osten. Die aus Silber gepr\u00e4gten Denare (Pfennige) sahen \u00fcberall anders aus, so dass sich mehr als 3000 verschiedene M\u00fcnztypen feststellen lassen. An der Pr\u00e4gung waren ca. 160-180 M\u00fcnzst\u00e4tten beteiligt, davon etwa 25-30 kontinuierlich und mit gr\u00f6\u00dferem Produktionsvolumen.","year_from":"911","year_until":"1200","autor":"Kluge, Bernd"},{"ikmk_timeline_id":"81","timeline_item":"Erzbisch\u00f6fe, Bisch\u00f6fe, \u00c4bte","description":"Um die wirtschaftlichen und politischen Potenzen der Kirche f\u00fcr das Reich und das eigene Seelenheil zu nutzen, ist die Kirche durch die K\u00f6nige im 10. und 11. Jh. im Deutschen Reich  mit Schenkungen bedacht worden. Zu diesen Schenkungen geh\u00f6rte auch die Verleihung des M\u00fcnzrechts. Auf diese Weise sind nahezu alle Erzbist\u00fcmer, Bist\u00fcmer und Reichsabteien in den Besitz des M\u00fcnzrechts gelangt, das die meisten auch ausge\u00fcbt haben. Die bis in die Neuzeit reichenden geistlichen M\u00fcnzpr\u00e4gungen in Deutschland haben ihre Wurzeln im 10. Jh.","year_from":"950","year_until":"1500","autor":"Kluge, Bernd"}],"text_right":{"short":"CC BY-SA 4.0","icon":"https:\/\/licensebuttons.net\/l\/by-sa\/4.0\/80x15.png","url":{"de":"https:\/\/creativecommons.org\/licenses\/by-sa\/4.0\/deed.de","en":"https:\/\/creativecommons.org\/licenses\/by-sa\/4.0\/deed.en"},"label":{"de":"Creative Commons Namensnennung - Weitergabe unter gleichen Bedingungen 4.0 International","en":"Creative Commons Attribution-ShareAlike 4.0 International"},"string":{"de":"Texte und Beschreibungen in diesem Online-Katalog stehen unter einer\u00a0<a href=\"https:\/\/creativecommons.org\/licenses\/by-sa\/4.0\/deed.de\" target=\"_blank\">CC BY-SA 4.0<\/a> Lizenz.","en":"Texts and descriptions of this catalogue are licensed <a href=\"https:\/\/creativecommons.org\/licenses\/by-sa\/4.0\/deed.en\" target=\"_blank\">CC BY-SA 4.0<\/a>."}},"lod_right":{"short":"PDM 1.0","icon":"https:\/\/licensebuttons.net\/p\/zero\/1.0\/80x15.png","url":{"de":"https:\/\/creativecommons.org\/publicdomain\/mark\/1.0\/deed.de","en":"https:\/\/creativecommons.org\/publicdomain\/mark\/1.0\/deed.en"},"label":{"de":"Public Domain Mark 1.0","en":"Public Domain Mark 1.0"},"string":{"de":"Verwendete LOD-Identifikatoren sind <a href=\"https:\/\/creativecommons.org\/publicdomain\/mark\/1.0\/deed.de\" target=\"_blank\">Public Domain Mark 1.0<\/a>\u00a0lizenziert.","en":"LOD ids used are licensed <a href=\"https:\/\/creativecommons.org\/publicdomain\/mark\/1.0\/deed.en\" target=\"_blank\">Public Domain Mark 1.0<\/a>."}},"image_restriction_id":0,"image_restriction":"free","image_right":{"short":"PDM 1.0","icon":"https:\/\/licensebuttons.net\/p\/zero\/1.0\/80x15.png","url":{"de":"https:\/\/creativecommons.org\/publicdomain\/mark\/1.0\/deed.de","en":"https:\/\/creativecommons.org\/publicdomain\/mark\/1.0\/deed.en"},"label":{"de":"Public Domain Mark 1.0","en":"Public Domain Mark 1.0"}}}