{"language_default":"de","language_more":[],"ikmk_mds_id":"18255270","ikmk_id":"57772","eLearning_completed":"0","primary_source_id":"0","title":"St. Gallen: Abtei","inventory_number":"","activated":"yes","item":{"ikmk_item_id":"1","ndp_uri":"https:\/\/ikmk.smb.museum\/ndp\/item\/1","item_de":"M\u00fcnze","item_en":"Coin","item_nomisma":"http:\/\/nomisma.org\/id\/coin"},"permalink":"https:\/\/ikmk.smb.museum\/object?id=18255270","permalink_source":null,"publisher":{"ikmk_publisher_id":13,"ndp_uri":"https:\/\/ikmk.smb.museum\/ndp\/owner\/13","publisher_name":"M\u00fcnzkabinett, Staatliche Museen zu Berlin - Stiftung Preu\u00dfischer Kulturbesitz","publisher_isil":"http:\/\/ld.zdb-services.de\/resource\/organisations\/DE-MUS-814819","publisher_isil_short":"DE-MUS-814819","UID":"http:\/\/ld.zdb-services.de\/resource\/organisations\/DE-MUS-814819\/18255270","legalBodyWeblink":"https:\/\/www.smb.museum\/museen-und-einrichtungen\/muenzkabinett\/home.html","nomisma_address":"http:\/\/nomisma.org\/id\/mk_berlin","author":"Stoess, Christian"},"owner":{"ikmk_owner_id":"13","owner_name":"Berlin, M\u00fcnzkabinett der Staatlichen Museen","owner_isil":"http:\/\/ld.zdb-services.de\/resource\/organisations\/DE-MUS-814819","owner_isil_short":"DE-MUS-814819","owner_www_address":"https:\/\/ikmk.smb.museum\/","nomisma_address":"http:\/\/nomisma.org\/id\/mk_berlin","ndp_uri":"https:\/\/ikmk.smb.museum\/ndp\/owner\/13","owner_type":{"de":"Eigentum","en":"Property","ikmk_type_id":"2","ndp_uri":"https:\/\/ikmk.smb.museum\/ndp\/status_of_property\/2"}},"ikmk_status_id":"7","status":{"de":"vorhanden","en":"present","ikmk_status_id":"7","ndp_uri":"https:\/\/ikmk.smb.museum\/ndp\/object_status\/7"},"nominal":{"ikmk_nominal_id":"731","nominal_de":"Denar (D\u00fcnnpfennig)","nominal_en":"Denar (D\u00fcnnpfennig)","nominal_nomisma_id":"","nominal_gnd_id":null,"info_de":null,"info_en":null,"ndp_uri":"https:\/\/ikmk.smb.museum\/ndp\/denomination\/731"},"patronage":"J\u00fcrg Richter","date_last":"2026-01-05 07:34:33","coin_status":[{"ikmk_coin_status_id":"114","coin_status_name_de":"Abtei St. Gallen","coin_status_name_en":"Saint Gallen Abbey","coin_status_nomisma_id":"http:\/\/nomisma.org\/id\/saint_gall_abbey","ndp_uri":"https:\/\/ikmk.smb.museum\/ndp\/class_status\/114"}],"mint":[{"ikmk_country_id":"65","country_ndp_url":"https:\/\/ikmk.smb.museum\/ndp\/country\/65","country_name_de":"Schweiz","country_name_en":"Switzerland","country_nomisma_id":"","country_geoname_id":"http:\/\/www.geonames.org\/2658434","ikmk_region_id":"345","region_ndp_uri":"https:\/\/ikmk.smb.museum\/ndp\/region\/345","region_name_de":"St. Gallen","region_name_en":null,"region_nomisma_id":"","region_geoname_id":"http:\/\/www.geonames.org\/2658821","ikmk_mint_id":"820","mint_ndp_uri":"https:\/\/ikmk.smb.museum\/ndp\/location\/820","mint_name":"St. Gallen","mint_name_de":"St. Gallen","mint_name_en":null,"mint_nomisma_id":"http:\/\/nomisma.org\/id\/st_gallen","mint_geoname_id":"http:\/\/www.geonames.org\/2658822"}],"material":{"ikmk_material_id":"1","material_name_de":"Silber","material_name_en":"Silver","material_nomisma_id":"http:\/\/nomisma.org\/id\/ar","ndp_uri":"https:\/\/ikmk.smb.museum\/ndp\/material\/1"},"diameter":"17 mm","die_axis":"7 h","weight":"0.46 g","accession":"1900\/277","access_year":"1900","access_type":{"ikmk_access_type_id":"1","access_type_name":"Kauf","access_type_nomisma_id":"","access_type_concept_id":"http:\/\/d-nb.info\/gnd\/4128692-3","ndp_uir":"https:\/\/ikmk.smb.museum\/ndp\/accession\/1"},"findspot":{"ikmk_country_id":"19","country_ndp_id":"https:\/\/ikmk.smb.museum\/ndp\/country\/19","country_name_de":"Deutschland","country_name_en":"Germany","country_nomisma_id":"http:\/\/nomisma.org\/id\/bundesrepublik_deutschland","country_geoname_id":"http:\/\/www.geonames.org\/2921044","ikmk_findspot_id":"149","findspot_ndp_uri":"https:\/\/ikmk.smb.museum\/ndp\/location\/149","findspot_name":"Fulda","findspot_nomisma_id":"http:\/\/nomisma.org\/id\/fulda","findspot_geonames_id":"http:\/\/www.geonames.org\/2923822"},"provenienz_extern":"","acquisition_date":"","avers":{"leg_trans":"Umschriftreste","leg_text":"","image_description":"Kopf eines Geistlichen (Stiftsheiliger oder Abt) von vorn, links nach au\u00dfen gewandter Krummstab.","foto_date":"2016-08-29","photographer":{"ikmk_photographer_id":"5","photographer_name":"Reinhard Saczewski","photographer_gnd":"","photographer_viaf":""},"path_thumbnail":"https:\/\/ikmk.smb.museum\/image\/18255270\/vs_opt.jpg","path_opt":"https:\/\/ikmk.smb.museum\/image\/18255270\/vs_opt.jpg","path_opt_rel":"\/data\/www\/001-ikmk\/mk-edit\/images\/n57\/57772\/vs_opt.jpg","path":"https:\/\/ikmk.smb.museum\/image\/18255270\/vs_org.jpg","path_org":"https:\/\/ikmk.smb.museum\/image\/18255270\/vs_org.jpg","image_timestamp":1643744044,"copyright":{"short":"PDM 1.0","url":"https:\/\/creativecommons.org\/publicdomain\/mark\/1.0\/","de":"Bilddateien sind lizenziert als&nbsp;<a href=\"https:\/\/creativecommons.org\/publicdomain\/mark\/1.0\/deed.de\" target=\"_blank\">Public Domain Mark 1.0<\/a>. Berlin, M\u00fcnzkabinett der Staatlichen Museen, 18255270. Aufnahme durch Reinhard Saczewski.","en":"Image files are licensed&nbsp;<a href=\"https:\/\/creativecommons.org\/publicdomain\/mark\/1.0\/deed.en\" target=\"_blank\">Public Domain Mark 1.0<\/a>. Berlin, M\u00fcnzkabinett der Staatlichen Museen, 18255270. Photographs by Reinhard Saczewski."}},"revers":{"leg_trans":"","leg_text":"","image_description":"Auf einem mit Perlen besetzten Kreuz das nach links gewandte Lamm Gottes.","foto_date":"2016-08-29","photographer":{"ikmk_photographer_id":"5","photographer_name":"Reinhard Saczewski","photographer_gnd":"","photographer_viaf":""},"path_thumbnail":"https:\/\/ikmk.smb.museum\/image\/18255270\/rs_opt.jpg","path_opt":"https:\/\/ikmk.smb.museum\/image\/18255270\/rs_opt.jpg","path_opt_rel":"\/data\/www\/001-ikmk\/mk-edit\/images\/n57\/57772\/rs_opt.jpg","path":"https:\/\/ikmk.smb.museum\/image\/18255270\/rs_org.jpg","path_org":"https:\/\/ikmk.smb.museum\/image\/18255270\/rs_org.jpg","image_timestamp":1643744044,"copyright":{"short":"PDM 1.0","url":"https:\/\/creativecommons.org\/publicdomain\/mark\/1.0\/","de":"Bilddateien sind lizenziert als&nbsp;<a href=\"https:\/\/creativecommons.org\/publicdomain\/mark\/1.0\/deed.de\" target=\"_blank\">Public Domain Mark 1.0<\/a>. Berlin, M\u00fcnzkabinett der Staatlichen Museen, 18255270. Aufnahme durch Reinhard Saczewski.","en":"Image files are licensed&nbsp;<a href=\"https:\/\/creativecommons.org\/publicdomain\/mark\/1.0\/deed.en\" target=\"_blank\">Public Domain Mark 1.0<\/a>. Berlin, M\u00fcnzkabinett der Staatlichen Museen, 18255270. Photographs by Reinhard Saczewski."}},"division":{"ikmk_division_id":"2","division_name_de":"Mittelalter","division_name_en":"Medieval Period"},"sub_division":{"ikmk_subdivision_id":"19","subdivision_name_de":"Hochmittelalter","subdivision_name_en":"High Middle Ages"},"literatur":"J. Menadier, Der M\u00fcnzschatz der St. Michaeliskirche zu Fulda, ZfN 22, 1900, 103-198. 295-311 bes. 152 Nr. 97 a (dieses St\u00fcck); H. Dannenberg, Die deutschen M\u00fcnzen der s\u00e4chsischen und fr\u00e4nkischen Kaiserzeit (1876-1905) Nr. 2122 (dieses St\u00fcck); B. Kluge, Deutsche M\u00fcnzgeschichte von der sp\u00e4ten Karolingerzeit bis zum Ende der Salier (1991) Nr. 509 (dieses St\u00fcck); J. Cahn, M\u00fcnzgeschichte von Konstanz und des Bodenseegebiets im Mittelalter bis zum Reichsm\u00fcnzgesetz von 1559 (1911) 442 Nr. 149 (dieses St\u00fcck, um 1120).","comment":"","period":{"ikmk_period_id":"14","name_de":"Hochmittelalter","name_en":"High Middle Ages","description_de":"Bezeichnung der Epoche zwischen 900 (teilweise auch 1000) und der Mitte des 13. Jahrhunderts.","description_en":"Term to describe the period between 900 (in some cases 1000) and the middle of the 13th century.","concept_id":"http:\/\/d-nb.info\/gnd\/7503822-5","ndp_uri":"https:\/\/ikmk.smb.museum\/ndp\/period\/14"},"year_start":"1100","year_end":"1120","date_verbal":"1100-1120","year_islam":"0","references":[{"ikmk_referenz_id":201,"souce":"Dannenberg","number":"2122","similar":"0"},{"ikmk_referenz_id":202,"souce":"DMG","number":"509","similar":"0"}],"manufacturing":[{"ikmk_manufacturing_id":"21","manufacturing_name_de":"gepr\u00e4gt","manufacturing_name_en":"struck","nomisma_id":"http:\/\/nomisma.org\/id\/struck","ndp_uri":"https:\/\/ikmk.smb.museum\/ndp\/manufacture\/21"}],"linked_persons_corporations":{"125":{"ikmk_type_id":"125","type_name_de":"Ver\u00e4u\u00dferer (an Museum)","type_name_en":"Vendor (to Museum)","type_nomisma_id":"","type_concept_id":"http:\/\/d-nb.info\/gnd\/4126928-7","ndp_id":"https:\/\/ikmk.smb.museum\/ndp\/type_for_person_and_corporation\/125","items":{"6883":{"ikmk_person_id":"6883","title_de":null,"first_name_de":"Adalbert","last_name_de":"Endert","vitalDates":"22.12.1850 - 20.06.1906","title_en":null,"first_name_en":"Adalbert","last_name_en":"Endert","corporation":"0","lod":{"https:\/\/d-nb.info\/gnd\/1071335669":"https:\/\/d-nb.info\/gnd\/1071335669","https:\/\/de.wikipedia.org\/wiki\/Adalbert_Endert":"https:\/\/de.wikipedia.org\/wiki\/Adalbert_Endert","https:\/\/viaf.org\/viaf\/316388770":"https:\/\/viaf.org\/viaf\/316388770","https:\/\/www.wikidata.org\/wiki\/Q347319":"https:\/\/www.wikidata.org\/wiki\/Q347319","https:\/\/ikmk.smb.museum\/ndp\/person\/6883":"https:\/\/ikmk.smb.museum\/ndp\/person\/6883"}}}}},"keywords":[{"ikmk_keyword_id":"50","keyword_de":"Christliche Ikonographie","keyword_gnd_uri":"http:\/\/d-nb.info\/gnd\/7502667-3","keyword_concept_uri":""},{"ikmk_keyword_id":"37","keyword_de":"Geistliche F\u00fcrsten","keyword_gnd_uri":"http:\/\/d-nb.info\/gnd\/4156371-2","keyword_concept_uri":"https:\/\/nomisma.org\/id\/clergy"},{"ikmk_keyword_id":"47","keyword_de":"Heilige","keyword_gnd_uri":"http:\/\/d-nb.info\/gnd\/4024055-1","keyword_concept_uri":"http:\/\/vocab.getty.edu\/aat\/300150555"},{"ikmk_keyword_id":"9","keyword_de":"Hochmittelalter, 10.-12. Jh.","keyword_gnd_uri":"http:\/\/d-nb.info\/gnd\/7503822-5","keyword_concept_uri":""},{"ikmk_keyword_id":"2","keyword_de":"Mittelalter","keyword_gnd_uri":"http:\/\/d-nb.info\/gnd\/4129108-6","keyword_concept_uri":"http:\/\/vocab.getty.edu\/aat\/300020756"},{"ikmk_keyword_id":"69","keyword_de":"Silber","keyword_gnd_uri":"http:\/\/d-nb.info\/gnd\/4133759-1","keyword_concept_uri":"http:\/\/www.nomisma.org\/id\/ar"},{"ikmk_keyword_id":"51","keyword_de":"Tiere","keyword_gnd_uri":"http:\/\/d-nb.info\/gnd\/4185464-0","keyword_concept_uri":""},{"ikmk_keyword_id":"19","keyword_de":"Westeuropa (ohne D)","keyword_gnd_uri":"http:\/\/d-nb.info\/gnd\/4079215-8","keyword_concept_uri":"http:\/\/vocab.getty.edu\/tgn\/4003761"}],"timeline_themes":[{"ikmk_timeline_id":"81","timeline_item":"Erzbisch\u00f6fe, Bisch\u00f6fe, \u00c4bte","description":"Um die wirtschaftlichen und politischen Potenzen der Kirche f\u00fcr das Reich und das eigene Seelenheil zu nutzen, ist die Kirche durch die K\u00f6nige im 10. und 11. Jh. im Deutschen Reich  mit Schenkungen bedacht worden. Zu diesen Schenkungen geh\u00f6rte auch die Verleihung des M\u00fcnzrechts. Auf diese Weise sind nahezu alle Erzbist\u00fcmer, Bist\u00fcmer und Reichsabteien in den Besitz des M\u00fcnzrechts gelangt, das die meisten auch ausge\u00fcbt haben. Die bis in die Neuzeit reichenden geistlichen M\u00fcnzpr\u00e4gungen in Deutschland haben ihre Wurzeln im 10. Jh.","year_from":"950","year_until":"1500","autor":"Kluge, Bernd"},{"ikmk_timeline_id":"39","timeline_item":"Renovatio monetae - regionale Pfennigw\u00e4hrungen","description":"Verrufungen (renovatio monetae) und W\u00e4hrungszwang (Wechselmonopol) kennzeichnen das System der hochmittelalterlichen Pfennigw\u00e4hrungen im Deutschen Reich. Zu bestimmten Stichtagen, meist j\u00e4hrlich, wurde das umlaufende Geld eingezogen (\u201everrufen\u201c). Wer Gesch\u00e4fte auf dem Markt machen wollte, war gezwungen, sein Geld dort umzuwechseln, wobei man meist f\u00fcr 12 alte nur 9 neue Pfennige erhielt, so da\u00df der M\u00fcnz- und Marktherr praktisch eine j\u00e4hrliche \u201eVerm\u00f6genssteuer\u201c von 25 Prozent erhob.","year_from":"1100","year_until":"1300","autor":"Kluge, Bernd"}],"text_right":{"short":"CC BY-SA 4.0","icon":"https:\/\/licensebuttons.net\/l\/by-sa\/4.0\/80x15.png","url":{"de":"https:\/\/creativecommons.org\/licenses\/by-sa\/4.0\/deed.de","en":"https:\/\/creativecommons.org\/licenses\/by-sa\/4.0\/deed.en"},"label":{"de":"Creative Commons Namensnennung - Weitergabe unter gleichen Bedingungen 4.0 International","en":"Creative Commons Attribution-ShareAlike 4.0 International"},"string":{"de":"Texte und Beschreibungen in diesem Online-Katalog stehen unter einer\u00a0<a href=\"https:\/\/creativecommons.org\/licenses\/by-sa\/4.0\/deed.de\" target=\"_blank\">CC BY-SA 4.0<\/a> Lizenz.","en":"Texts and descriptions of this catalogue are licensed <a href=\"https:\/\/creativecommons.org\/licenses\/by-sa\/4.0\/deed.en\" target=\"_blank\">CC BY-SA 4.0<\/a>."}},"lod_right":{"short":"PDM 1.0","icon":"https:\/\/licensebuttons.net\/p\/zero\/1.0\/80x15.png","url":{"de":"https:\/\/creativecommons.org\/publicdomain\/mark\/1.0\/deed.de","en":"https:\/\/creativecommons.org\/publicdomain\/mark\/1.0\/deed.en"},"label":{"de":"Public Domain Mark 1.0","en":"Public Domain Mark 1.0"},"string":{"de":"Verwendete LOD-Identifikatoren sind <a href=\"https:\/\/creativecommons.org\/publicdomain\/mark\/1.0\/deed.de\" target=\"_blank\">Public Domain Mark 1.0<\/a>\u00a0lizenziert.","en":"LOD ids used are licensed <a href=\"https:\/\/creativecommons.org\/publicdomain\/mark\/1.0\/deed.en\" target=\"_blank\">Public Domain Mark 1.0<\/a>."}},"image_restriction_id":0,"image_restriction":"free","image_right":{"short":"PDM 1.0","icon":"https:\/\/licensebuttons.net\/p\/zero\/1.0\/80x15.png","url":{"de":"https:\/\/creativecommons.org\/publicdomain\/mark\/1.0\/deed.de","en":"https:\/\/creativecommons.org\/publicdomain\/mark\/1.0\/deed.en"},"label":{"de":"Public Domain Mark 1.0","en":"Public Domain Mark 1.0"}}}